<chromosome id="8277" primary-parent-id="8200"><neuron id="165" type="in" activation="sigmoid"/>
<neuron id="166" type="in" activation="sigmoid"/>
<neuron id="167" type="in" activation="sigmoid"/>
<neuron id="168" type="in" activation="sigmoid"/>
<neuron id="169" type="in" activation="sigmoid"/>
<neuron id="170" type="in" activation="sigmoid"/>
<neuron id="171" type="in" activation="sigmoid"/>
<neuron id="172" type="in" activation="sigmoid"/>
<neuron id="173" type="in" activation="sigmoid"/>
<neuron id="174" type="in" activation="sigmoid"/>
<neuron id="175" type="in" activation="sigmoid"/>
<neuron id="176" type="in" activation="sigmoid"/>
<neuron id="177" type="in" activation="sigmoid"/>
<neuron id="178" type="in" activation="sigmoid"/>
<neuron id="179" type="in" activation="sigmoid"/>
<neuron id="180" type="in" activation="sigmoid"/>
<neuron id="181" type="in" activation="sigmoid"/>
<neuron id="182" type="in" activation="sigmoid"/>
<neuron id="183" type="in" activation="sigmoid"/>
<neuron id="184" type="in" activation="sigmoid"/>
<neuron id="185" type="in" activation="sigmoid"/>
<neuron id="186" type="in" activation="sigmoid"/>
<neuron id="187" type="in" activation="sigmoid"/>
<neuron id="188" type="out" activation="sigmoid"/>
<neuron id="189" type="out" activation="sigmoid"/>
<neuron id="190" type="out" activation="sigmoid"/>
<neuron id="191" type="out" activation="sigmoid"/>
<neuron id="192" type="hid" activation="sigmoid"/>
<connection id="193" src-id="165" dest-id="192" weight="0.35059603384183385"/>
<connection id="194" src-id="166" dest-id="192" weight="1.1508990008177535"/>
<connection id="196" src-id="168" dest-id="192" weight="-0.8848826643157561"/>
<connection id="200" src-id="172" dest-id="192" weight="1.7069807744279917"/>
<connection id="206" src-id="178" dest-id="192" weight="-2.31138013983247"/>
<connection id="208" src-id="180" dest-id="192" weight="-1.1425036312546837"/>
<connection id="209" src-id="181" dest-id="192" weight="-0.8151280541244683"/>
<connection id="211" src-id="183" dest-id="192" weight="-2.2044128648881642"/>
<connection id="212" src-id="184" dest-id="192" weight="0.4554740436422239"/>
<connection id="213" src-id="185" dest-id="192" weight="10.770128966997445"/>
<connection id="214" src-id="186" dest-id="192" weight="0.599959135055542"/>
<connection id="215" src-id="187" dest-id="192" weight="2.0138828721673727"/>
<connection id="216" src-id="192" dest-id="188" weight="-0.23519940145885143"/>
<connection id="217" src-id="192" dest-id="189" weight="-7.929202349159472"/>
<connection id="218" src-id="192" dest-id="190" weight="0.4272550344467163"/>
<connection id="219" src-id="192" dest-id="191" weight="-3.2906102512872017"/>
<connection id="241" src-id="174" dest-id="184" weight="0.8581762105028163"/>
<connection id="242" src-id="166" dest-id="186" weight="-11.950307165448557"/>
<connection id="243" src-id="191" dest-id="165" weight="2.8834033563447576"/>
<connection id="245" src-id="168" dest-id="166" weight="-0.541558027267456"/>
<connection id="246" src-id="186" dest-id="173" weight="1.4955389076840775"/>
<connection id="247" src-id="170" dest-id="191" weight="0.7920471429824829"/>
<connection id="249" src-id="176" dest-id="168" weight="-0.6675299406051636"/>
<connection id="252" src-id="173" dest-id="191" weight="-1.7176609795576467"/>
<connection id="254" src-id="177" dest-id="189" weight="0.903911366745959"/>
<connection id="256" src-id="167" dest-id="180" weight="10.866789816979875"/>
<connection id="258" src-id="175" dest-id="184" weight="0.516948705778449"/>
<connection id="263" src-id="175" dest-id="182" weight="-6.283954970065758"/>
<connection id="264" src-id="167" dest-id="165" weight="-0.6851828629231755"/>
<connection id="266" src-id="189" dest-id="176" weight="-5.3167379994333155"/>
<connection id="267" src-id="186" dest-id="174" weight="-2.331351264024713"/>
<connection id="268" src-id="165" dest-id="188" weight="-2.8736982599345353"/>
<connection id="270" src-id="173" dest-id="166" weight="-2.066611290748721"/>
<connection id="271" src-id="173" dest-id="187" weight="-0.7488040801507299"/>
<connection id="273" src-id="188" dest-id="176" weight="1.3085920276323046"/>
<connection id="276" src-id="184" dest-id="186" weight="-0.3526792468011377"/>
<connection id="278" src-id="174" dest-id="180" weight="-0.5591326951980591"/>
<connection id="281" src-id="170" dest-id="168" weight="-2.969369810111607"/>
<connection id="282" src-id="183" dest-id="182" weight="3.972987487824686"/>
<connection id="284" src-id="187" dest-id="187" weight="0.6518663167953491"/>
<connection id="286" src-id="170" dest-id="171" weight="-0.005006551742553711"/>
<connection id="288" src-id="190" dest-id="166" weight="-1.6958263480886475"/>
<connection id="289" src-id="174" dest-id="172" weight="0.30921920462882646"/>
<connection id="290" src-id="166" dest-id="172" weight="0.857476632564718"/>
<connection id="294" src-id="168" dest-id="173" weight="1.5511591679461407"/>
<connection id="295" src-id="186" dest-id="183" weight="-2.754980355968579"/>
<connection id="296" src-id="188" dest-id="181" weight="-8.07426223905917"/>
<connection id="299" src-id="174" dest-id="176" weight="-2.3462746496313036"/>
<connection id="300" src-id="182" dest-id="167" weight="-2.5323534241687637"/>
<connection id="301" src-id="165" dest-id="172" weight="-2.4816722639106334"/>
<connection id="302" src-id="174" dest-id="165" weight="-0.6056270599365234"/>
<connection id="304" src-id="172" dest-id="190" weight="-2.602110854805527"/>
<connection id="306" src-id="172" dest-id="167" weight="2.4818198733796386"/>
<connection id="307" src-id="165" dest-id="174" weight="-5.89004914734346"/>
<connection id="308" src-id="182" dest-id="186" weight="-5.209371102620096"/>
<connection id="311" src-id="189" dest-id="189" weight="2.797343884361044"/>
<connection id="312" src-id="182" dest-id="168" weight="-0.40735161304473877"/>
<connection id="318" src-id="165" dest-id="182" weight="-1.361584662817501"/>
<connection id="320" src-id="165" dest-id="177" weight="2.3638023307955316"/>
<connection id="322" src-id="176" dest-id="190" weight="3.6499245581162176"/>
<connection id="323" src-id="168" dest-id="177" weight="-9.577875972580982"/>
<connection id="326" src-id="167" dest-id="172" weight="0.7271794823835735"/>
<connection id="327" src-id="167" dest-id="179" weight="1.0681363340398524"/>
<connection id="328" src-id="188" dest-id="183" weight="-2.3618437506361776"/>
<connection id="330" src-id="176" dest-id="178" weight="0.4054758548736572"/>
<connection id="331" src-id="169" dest-id="173" weight="-0.21757232080552735"/>
<connection id="332" src-id="185" dest-id="166" weight="5.202337754609913"/>
<connection id="334" src-id="191" dest-id="167" weight="6.15488497443062"/>
<connection id="335" src-id="177" dest-id="183" weight="-0.33417487144470215"/>
<connection id="337" src-id="178" dest-id="175" weight="2.6422499570447013"/>
<connection id="338" src-id="187" dest-id="186" weight="-3.190045732078728"/>
<connection id="342" src-id="168" dest-id="178" weight="0.5741845369338989"/>
<connection id="348" src-id="178" dest-id="183" weight="-0.7824251651763916"/>
<connection id="349" src-id="170" dest-id="184" weight="-4.68672037502545"/>
<connection id="350" src-id="172" dest-id="174" weight="5.601626193578019"/>
<connection id="353" src-id="179" dest-id="180" weight="0.6592544317245483"/>
<connection id="354" src-id="187" dest-id="182" weight="2.0983583590226775"/>
<connection id="356" src-id="177" dest-id="187" weight="0.23229552874910397"/>
<connection id="357" src-id="176" dest-id="188" weight="1.26414892421226"/>
<connection id="358" src-id="181" dest-id="191" weight="-0.15902399626219"/>
<connection id="359" src-id="183" dest-id="165" weight="1.8612837139614555"/>
<connection id="360" src-id="171" dest-id="187" weight="-0.591867162999163"/>
<connection id="363" src-id="177" dest-id="172" weight="-0.04757037617508253"/>
<connection id="367" src-id="172" dest-id="184" weight="0.51732337474823"/>
<connection id="368" src-id="172" dest-id="181" weight="-0.14595425415752689"/>
<connection id="369" src-id="176" dest-id="180" weight="-5.670561600606601"/>
<connection id="371" src-id="173" dest-id="188" weight="5.375320258064996"/>
<connection id="372" src-id="179" dest-id="178" weight="-0.8076221076055756"/>
<connection id="373" src-id="167" dest-id="173" weight="0.7224806547164917"/>
<connection id="374" src-id="166" dest-id="166" weight="0.8135396353307672"/>
<connection id="376" src-id="189" dest-id="188" weight="1.2240796946790802"/>
<connection id="379" src-id="182" dest-id="189" weight="0.3496223250924231"/>
<connection id="380" src-id="191" dest-id="172" weight="-1.926095652033739"/>
<connection id="383" src-id="183" dest-id="173" weight="-4.51316839231117"/>
<connection id="384" src-id="166" dest-id="165" weight="0.2632240056991577"/>
<connection id="385" src-id="168" dest-id="190" weight="-0.21883618831634521"/>
<connection id="387" src-id="181" dest-id="165" weight="0.4001725912094116"/>
<connection id="388" src-id="172" dest-id="169" weight="2.672211836226446"/>
<connection id="390" src-id="165" dest-id="170" weight="0.9560023546218872"/>
<connection id="391" src-id="188" dest-id="192" weight="0.31191742420196533"/>
<connection id="392" src-id="175" dest-id="191" weight="-1.0946004703537358"/>
<connection id="393" src-id="176" dest-id="171" weight="0.8008561134338379"/>
<connection id="394" src-id="171" dest-id="173" weight="-1.6060284417649686"/>
<connection id="395" src-id="167" dest-id="171" weight="0.38987241140748563"/>
<connection id="396" src-id="178" dest-id="168" weight="0.3765376806259155"/>
<connection id="398" src-id="183" dest-id="177" weight="-1.090256569773253"/>
<connection id="400" src-id="170" dest-id="177" weight="-5.697009891218194"/>
<connection id="401" src-id="170" dest-id="172" weight="0.27981245517730713"/>
<connection id="403" src-id="184" dest-id="187" weight="7.955428751967039"/>
<connection id="404" src-id="188" dest-id="179" weight="-0.24194669723510742"/>
<connection id="406" src-id="184" dest-id="178" weight="0.19661648962968692"/>
<connection id="407" src-id="175" dest-id="166" weight="-2.9447344880889257"/>
<connection id="409" src-id="180" dest-id="165" weight="-5.450055486806645"/>
<connection id="410" src-id="191" dest-id="170" weight="-0.1482464075088501"/>
<connection id="414" src-id="170" dest-id="181" weight="0.5441603660583496"/>
<connection id="415" src-id="167" dest-id="190" weight="5.801829775450748"/>
<connection id="416" src-id="181" dest-id="166" weight="0.7743908166885376"/>
<connection id="417" src-id="185" dest-id="183" weight="0.3570211399323875"/>
<connection id="419" src-id="185" dest-id="173" weight="-0.7167481097788567"/>
<connection id="420" src-id="185" dest-id="191" weight="0.7783293724060059"/>
<connection id="422" src-id="167" dest-id="188" weight="8.989795089000571"/>
<connection id="423" src-id="181" dest-id="183" weight="5.452130831480174"/>
<connection id="425" src-id="181" dest-id="184" weight="-0.9147342443466187"/>
<connection id="426" src-id="165" dest-id="176" weight="-0.591795802116394"/>
<connection id="427" src-id="192" dest-id="176" weight="3.5802452860395713"/>
<connection id="428" src-id="174" dest-id="169" weight="-5.057010075361079"/>
<connection id="429" src-id="169" dest-id="181" weight="0.529291033744812"/>
<connection id="430" src-id="172" dest-id="165" weight="2.7333226389225826"/>
<connection id="431" src-id="167" dest-id="167" weight="0.9638978242874146"/>
<connection id="432" src-id="183" dest-id="175" weight="-1.9344278854585306"/>
<connection id="433" src-id="187" dest-id="188" weight="-2.0664937817594105"/>
<connection id="434" src-id="170" dest-id="173" weight="-1.00189269724182"/>
<connection id="438" src-id="167" dest-id="175" weight="1.1798348466311501"/>
<connection id="439" src-id="171" dest-id="167" weight="-0.40040624141693115"/>
<connection id="440" src-id="187" dest-id="190" weight="0.6746950149536133"/>
<connection id="441" src-id="179" dest-id="182" weight="0.08358518187772786"/>
<connection id="442" src-id="176" dest-id="185" weight="0.43948097221027027"/>
<connection id="443" src-id="188" dest-id="185" weight="-1.3127947767803723"/>
<connection id="444" src-id="170" dest-id="176" weight="-3.899638922102821"/>
<connection id="447" src-id="177" dest-id="186" weight="2.712133998529686"/>
<connection id="448" src-id="181" dest-id="189" weight="-3.028778395148997"/>
<connection id="456" src-id="176" dest-id="184" weight="-0.7297521829605103"/>
<connection id="458" src-id="192" dest-id="183" weight="-0.08775210380554199"/>
<connection id="459" src-id="173" dest-id="185" weight="-9.17183259764877"/>
<connection id="460" src-id="171" dest-id="190" weight="3.3480517131431173"/>
<connection id="461" src-id="180" dest-id="169" weight="0.3707336281091135"/>
<connection id="462" src-id="186" dest-id="182" weight="-6.976765559404226"/>
<connection id="464" src-id="182" dest-id="184" weight="-1.9003080420684704"/>
<connection id="465" src-id="184" dest-id="184" weight="0.9805008172988892"/>
<connection id="467" src-id="186" dest-id="181" weight="-3.355526777584849"/>
<connection id="468" src-id="181" dest-id="171" weight="-5.941879136884636"/>
<connection id="470" src-id="188" dest-id="175" weight="0.046747565269470215"/>
<connection id="472" src-id="185" dest-id="175" weight="1.8984399435988388"/>
<connection id="473" src-id="187" dest-id="185" weight="5.016839970355433"/>
<connection id="475" src-id="165" dest-id="175" weight="0.9175596237182617"/>
<connection id="480" src-id="169" dest-id="177" weight="0.14118357304602913"/>
<connection id="482" src-id="176" dest-id="170" weight="4.364631139448639"/>
<connection id="484" src-id="187" dest-id="174" weight="-5.457387801744589"/>
<connection id="487" src-id="188" dest-id="184" weight="3.9585805136987195"/>
<connection id="488" src-id="184" dest-id="190" weight="-0.6927272033240044"/>
<connection id="489" src-id="176" dest-id="174" weight="-1.3539426240415868"/>
<connection id="490" src-id="191" dest-id="171" weight="-0.035315513610839844"/>
<connection id="492" src-id="165" dest-id="185" weight="0.38069963455200195"/>
<connection id="493" src-id="185" dest-id="190" weight="-1.6211523851268734"/>
<connection id="494" src-id="182" dest-id="170" weight="-1.7542690216005057"/>
<connection id="497" src-id="171" dest-id="183" weight="1.8830792394481106"/>
<connection id="498" src-id="166" dest-id="185" weight="-3.2415370236659453"/>
<connection id="500" src-id="179" dest-id="168" weight="0.9934402704238892"/>
<connection id="501" src-id="174" dest-id="174" weight="-0.8009899191442683"/>
<connection id="502" src-id="183" dest-id="181" weight="0.25732481479644775"/>
<connection id="503" src-id="189" dest-id="184" weight="0.7237152656628507"/>
<connection id="505" src-id="184" dest-id="168" weight="4.893634696007365"/>
<connection id="508" src-id="184" dest-id="165" weight="-2.0129743607235824"/>
<connection id="509" src-id="171" dest-id="182" weight="0.39934101772491126"/>
<connection id="510" src-id="185" dest-id="186" weight="2.927658128551322"/>
<connection id="511" src-id="165" dest-id="191" weight="2.5227431882393256"/>
<connection id="512" src-id="190" dest-id="182" weight="6.20450936115622"/>
<connection id="514" src-id="191" dest-id="177" weight="-0.4616018533706665"/>
<connection id="520" src-id="167" dest-id="185" weight="-0.04501938819885254"/>
<connection id="522" src-id="190" dest-id="192" weight="-1.3230020052496991"/>
<connection id="525" src-id="183" dest-id="172" weight="0.04002575070919198"/>
<connection id="526" src-id="186" dest-id="170" weight="2.0760303193920033"/>
<connection id="527" src-id="170" dest-id="182" weight="1.4427868200806482"/>
<connection id="528" src-id="190" dest-id="170" weight="8.003340928431092"/>
<connection id="529" src-id="181" dest-id="176" weight="-0.5383753816764727"/>
<connection id="530" src-id="191" dest-id="191" weight="-7.954759946761451"/>
<connection id="533" src-id="190" dest-id="173" weight="-3.429326665395222"/>
<connection id="535" src-id="182" dest-id="185" weight="0.25746890270159195"/>
<connection id="538" src-id="183" dest-id="190" weight="0.725135087966919"/>
<connection id="539" src-id="179" dest-id="185" weight="5.4470197914177865"/>
<connection id="544" src-id="173" dest-id="170" weight="-0.637299656867981"/>
<connection id="545" src-id="171" dest-id="186" weight="2.9673271724821264"/>
<connection id="546" src-id="192" dest-id="165" weight="-2.0639200590780917"/>
<connection id="548" src-id="185" dest-id="189" weight="3.67303477471844"/>
<connection id="549" src-id="177" dest-id="184" weight="-3.903885233940876"/>
<connection id="550" src-id="185" dest-id="174" weight="-2.546210357062479"/>
<connection id="551" src-id="176" dest-id="187" weight="-0.31882715225219727"/>
<connection id="552" src-id="165" dest-id="165" weight="-4.0313417297209515"/>
<connection id="553" src-id="171" dest-id="170" weight="5.591906325012857"/>
<connection id="555" src-id="177" dest-id="165" weight="0.8958914279937744"/>
<connection id="556" src-id="189" dest-id="183" weight="-1.4853768016914195"/>
<connection id="559" src-id="176" dest-id="181" weight="-4.162538690350509"/>
<connection id="560" src-id="184" dest-id="189" weight="0.614016254776707"/>
<connection id="565" src-id="192" dest-id="175" weight="-1.0724124779084279"/>
<connection id="567" src-id="186" dest-id="177" weight="2.708478703233523"/>
<connection id="569" src-id="174" dest-id="191" weight="-0.035569410415434544"/>
<connection id="570" src-id="177" dest-id="191" weight="2.4096379572886057"/>
<connection id="571" src-id="177" dest-id="174" weight="-0.6491607427597046"/>
<connection id="572" src-id="175" dest-id="177" weight="4.816291844498604"/>
<connection id="574" src-id="166" dest-id="182" weight="-0.17204495845061096"/>
<connection id="577" src-id="169" dest-id="176" weight="0.6399928331375122"/>
<connection id="578" src-id="169" dest-id="191" weight="-1.2978967607956677"/>
<connection id="580" src-id="169" dest-id="178" weight="1.5365155846223568"/>
<connection id="581" src-id="176" dest-id="167" weight="2.990305587286152"/>
<connection id="582" src-id="179" dest-id="177" weight="1.184876476026921"/>
<connection id="584" src-id="179" dest-id="188" weight="-2.066222739984779"/>
<connection id="587" src-id="170" dest-id="188" weight="3.5440532024850038"/>
<connection id="589" src-id="169" dest-id="186" weight="-0.4909935297010084"/>
<connection id="590" src-id="180" dest-id="168" weight="-2.2061001721436098"/>
<connection id="592" src-id="182" dest-id="191" weight="0.8140473549529339"/>
<connection id="593" src-id="191" dest-id="185" weight="0.16865766048431396"/>
<connection id="594" src-id="187" dest-id="175" weight="5.471428223219251"/>
<connection id="596" src-id="184" dest-id="180" weight="-0.1387389898300171"/>
<connection id="599" src-id="186" dest-id="166" weight="-1.717764170885609"/>
<connection id="601" src-id="171" dest-id="172" weight="-2.5328076281276433"/>
<connection id="603" src-id="187" dest-id="180" weight="-4.281689946287843"/>
<connection id="606" src-id="165" dest-id="186" weight="0.3235232996558528"/>
<connection id="607" src-id="181" dest-id="181" weight="5.854845926263723"/>
<connection id="608" src-id="190" dest-id="184" weight="2.156960037356736"/>
<connection id="610" src-id="175" dest-id="181" weight="1.8967362496180558"/>
<connection id="611" src-id="181" dest-id="182" weight="5.0178290309523135"/>
<connection id="612" src-id="186" dest-id="190" weight="1.9568414218243402"/>
<connection id="613" src-id="182" dest-id="182" weight="-2.1254573853227825"/>
<connection id="614" src-id="184" dest-id="175" weight="-2.42862776616328"/>
<connection id="617" src-id="189" dest-id="186" weight="1.8015577543393313"/>
<connection id="620" src-id="174" dest-id="181" weight="-2.77531805284611"/>
<connection id="622" src-id="192" dest-id="186" weight="-0.09044122695922852"/>
<connection id="624" src-id="178" dest-id="191" weight="0.987004280090332"/>
<connection id="627" src-id="170" dest-id="190" weight="0.3334094285964966"/>
<connection id="630" src-id="189" dest-id="172" weight="2.4699585109575244"/>
<connection id="631" src-id="172" dest-id="182" weight="-0.26983070373535156"/>
<connection id="632" src-id="171" dest-id="181" weight="0.9928977817986089"/>
<connection id="633" src-id="169" dest-id="185" weight="-0.980304166382131"/>
<connection id="634" src-id="181" dest-id="174" weight="-0.9194527864456177"/>
<connection id="635" src-id="171" dest-id="177" weight="-0.6467894315719604"/>
<connection id="636" src-id="179" dest-id="181" weight="0.046727776527404785"/>
<connection id="638" src-id="171" dest-id="171" weight="-2.6873173090081264"/>
<connection id="639" src-id="172" dest-id="179" weight="-1.8063549507582852"/>
<connection id="640" src-id="174" dest-id="188" weight="6.384141304516249"/>
<connection id="644" src-id="176" dest-id="183" weight="4.784473746707264"/>
<connection id="646" src-id="182" dest-id="171" weight="-0.9063881355249763"/>
<connection id="648" src-id="180" dest-id="189" weight="0.4479857798488438"/>
<connection id="649" src-id="167" dest-id="166" weight="-7.41474910254075"/>
<connection id="651" src-id="192" dest-id="166" weight="1.480423452249117"/>
<connection id="653" src-id="180" dest-id="167" weight="-13.247696764026754"/>
<connection id="654" src-id="188" dest-id="170" weight="-5.098503947433047"/>
<connection id="655" src-id="177" dest-id="169" weight="-0.47428425964615684"/>
<connection id="656" src-id="188" dest-id="173" weight="7.564316854221893"/>
<connection id="658" src-id="183" dest-id="171" weight="-2.308890620419415"/>
<connection id="659" src-id="165" dest-id="168" weight="1.392917051223524"/>
<connection id="660" src-id="169" dest-id="182" weight="1.5324059434401582"/>
<connection id="661" src-id="190" dest-id="168" weight="-0.393094539642334"/>
<connection id="664" src-id="181" dest-id="178" weight="-0.944480299949646"/>
<connection id="665" src-id="186" dest-id="165" weight="1.1530160262708558"/>
<connection id="669" src-id="189" dest-id="191" weight="-0.5563616419552051"/>
<connection id="674" src-id="192" dest-id="184" weight="-3.840657458696568"/>
<connection id="675" src-id="182" dest-id="178" weight="-0.9045852422714233"/>
<connection id="678" src-id="190" dest-id="187" weight="-0.4739080839179912"/>
<connection id="683" src-id="175" dest-id="185" weight="-0.2204911708831787"/>
<connection id="684" src-id="182" dest-id="173" weight="3.7626147608390683"/>
<connection id="687" src-id="174" dest-id="185" weight="-0.9397052190281768"/>
<connection id="688" src-id="179" dest-id="173" weight="-0.7481024621525181"/>
<connection id="690" src-id="189" dest-id="182" weight="-3.73700246928558"/>
<connection id="691" src-id="169" dest-id="184" weight="-4.318820238165365"/>
<connection id="692" src-id="179" dest-id="187" weight="1.4436331268436506"/>
<connection id="693" src-id="187" dest-id="167" weight="-0.5485996007919312"/>
<connection id="694" src-id="173" dest-id="178" weight="0.09032037349038813"/>
<connection id="696" src-id="180" dest-id="181" weight="-0.15584540367126465"/>
<connection id="697" src-id="167" dest-id="184" weight="-4.995039583530984"/>
<connection id="698" src-id="172" dest-id="186" weight="2.9983821666350066"/>
<connection id="699" src-id="172" dest-id="177" weight="2.3661197514280703"/>
<connection id="703" src-id="175" dest-id="179" weight="-0.5044009685516357"/>
<connection id="704" src-id="190" dest-id="179" weight="-2.3199729574379067"/>
<connection id="706" src-id="177" dest-id="180" weight="-0.25509161024770566"/>
<connection id="708" src-id="165" dest-id="190" weight="-1.8454952220651395"/>
<connection id="709" src-id="172" dest-id="175" weight="-0.21249633908612986"/>
<connection id="710" src-id="172" dest-id="176" weight="0.4827643632888794"/>
<connection id="714" src-id="186" dest-id="179" weight="0.15467299573134774"/>
<connection id="720" src-id="168" dest-id="183" weight="0.7521264055814526"/>
<connection id="722" src-id="176" dest-id="165" weight="-0.05363917350769043"/>
<connection id="725" src-id="178" dest-id="172" weight="-15.990388733559726"/>
<connection id="726" src-id="187" dest-id="166" weight="0.4892629648918704"/>
<connection id="727" src-id="174" dest-id="179" weight="2.394755940908109"/>
<connection id="728" src-id="165" dest-id="179" weight="-4.551759254180249"/>
<connection id="735" src-id="176" dest-id="166" weight="-0.15168416500091553"/>
<connection id="736" src-id="184" dest-id="185" weight="0.9611111879348755"/>
<connection id="748" src-id="179" dest-id="170" weight="5.028680330893684"/>
<connection id="749" src-id="188" dest-id="190" weight="-1.300889634756833"/>
<connection id="750" src-id="174" dest-id="173" weight="-0.01475059986114502"/>
<connection id="752" src-id="185" dest-id="170" weight="-1.608698526643874"/>
<connection id="753" src-id="175" dest-id="171" weight="5.4461726860812245"/>
<connection id="755" src-id="184" dest-id="191" weight="0.4078391737172357"/>
<connection id="757" src-id="173" dest-id="186" weight="-3.137951634940329"/>
<connection id="758" src-id="185" dest-id="188" weight="0.13908104292421986"/>
<connection id="760" src-id="175" dest-id="169" weight="-3.433354062685665"/>
<connection id="764" src-id="190" dest-id="178" weight="0.42865610122680664"/>
<connection id="765" src-id="166" dest-id="168" weight="2.6636271676117493"/>
<connection id="767" src-id="187" dest-id="183" weight="0.5334215904811548"/>
<connection id="768" src-id="189" dest-id="169" weight="-3.305214214598319"/>
<connection id="769" src-id="180" dest-id="166" weight="1.0206452381102324"/>
<connection id="770" src-id="189" dest-id="166" weight="1.2071419825486123"/>
<connection id="771" src-id="171" dest-id="168" weight="2.3043168594320806"/>
<connection id="775" src-id="179" dest-id="171" weight="-2.5714443721740796"/>
<connection id="776" src-id="169" dest-id="165" weight="-1.3594555847999796"/>
<connection id="777" src-id="188" dest-id="165" weight="1.6110538878465457"/>
<connection id="781" src-id="168" dest-id="172" weight="2.840582139490021"/>
<connection id="785" src-id="177" dest-id="175" weight="-1.9654516560632405"/>
<connection id="786" src-id="184" dest-id="166" weight="12.748253242462166"/>
<connection id="787" src-id="170" dest-id="175" weight="2.3151086039311903"/>
<connection id="789" src-id="185" dest-id="182" weight="-0.575800895690918"/>
<connection id="792" src-id="183" dest-id="170" weight="-4.461550957991857"/>
<connection id="794" src-id="168" dest-id="165" weight="0.721082435400061"/>
<connection id="795" src-id="188" dest-id="178" weight="1.088777097160164"/>
<connection id="796" src-id="174" dest-id="182" weight="-0.5182578563690186"/>
<connection id="797" src-id="181" dest-id="186" weight="-6.068847983304247"/>
<connection id="799" src-id="169" dest-id="170" weight="2.1459162725907506"/>
<connection id="801" src-id="181" dest-id="177" weight="1.7656346574574755"/>
<connection id="802" src-id="189" dest-id="179" weight="2.238071295235268"/>
<connection id="803" src-id="190" dest-id="175" weight="6.606473691349619"/>
<connection id="804" src-id="189" dest-id="185" weight="-2.0305087288297656"/>
<connection id="807" src-id="172" dest-id="188" weight="2.74999063928105"/>
<connection id="809" src-id="185" dest-id="185" weight="-1.470267741428375"/>
<connection id="813" src-id="183" dest-id="166" weight="-1.4132440545304008"/>
<connection id="816" src-id="166" dest-id="177" weight="-0.1815379782399268"/>
<connection id="817" src-id="179" dest-id="184" weight="4.216808128352361"/>
<connection id="820" src-id="192" dest-id="168" weight="3.668554613777637"/>
<connection id="822" src-id="188" dest-id="169" weight="-11.391873197647325"/>
<connection id="825" src-id="178" dest-id="177" weight="7.066087027249645"/>
<connection id="828" src-id="178" dest-id="184" weight="0.9878835678100586"/>
<connection id="829" src-id="188" dest-id="189" weight="-8.342017729534126"/>
<connection id="830" src-id="175" dest-id="189" weight="0.275143027305603"/>
<connection id="831" src-id="170" dest-id="187" weight="2.7578420341767695"/>
<connection id="832" src-id="180" dest-id="185" weight="-0.9534131288528442"/>
<connection id="833" src-id="178" dest-id="187" weight="-0.3555262088775635"/>
<connection id="837" src-id="175" dest-id="175" weight="3.6434677528228203"/>
<connection id="839" src-id="169" dest-id="183" weight="0.3080270290374756"/>
<connection id="840" src-id="183" dest-id="168" weight="-6.785680745367905"/>
<connection id="841" src-id="191" dest-id="179" weight="-0.07925927639007568"/>
<connection id="843" src-id="172" dest-id="185" weight="1.7609725664776366"/>
<connection id="846" src-id="180" dest-id="175" weight="-8.033085365569947"/>
<connection id="848" src-id="174" dest-id="170" weight="-0.607994556427002"/>
<connection id="849" src-id="180" dest-id="190" weight="-2.1334559714643424"/>
<connection id="850" src-id="167" dest-id="177" weight="-0.8349450826644897"/>
<connection id="851" src-id="166" dest-id="171" weight="-0.40225350856781006"/>
<connection id="852" src-id="174" dest-id="177" weight="-0.08504331111907959"/>
<connection id="854" src-id="172" dest-id="178" weight="-3.42562863625688"/>
<connection id="855" src-id="187" dest-id="171" weight="2.647193771016167"/>
<connection id="856" src-id="178" dest-id="176" weight="-2.9954704470242"/>
<connection id="857" src-id="189" dest-id="175" weight="2.98810290303943"/>
<connection id="859" src-id="177" dest-id="171" weight="1.0407001654873052"/>
<connection id="860" src-id="168" dest-id="189" weight="-0.2931292979601924"/>
<connection id="862" src-id="171" dest-id="189" weight="-1.5731524729336472"/>
<connection id="863" src-id="165" dest-id="171" weight="-1.2501175853006457"/>
<connection id="864" src-id="182" dest-id="166" weight="-4.886263821810874"/>
<connection id="866" src-id="173" dest-id="172" weight="-1.0301139099097405"/>
<connection id="872" src-id="187" dest-id="172" weight="-0.8171887397766113"/>
<connection id="874" src-id="181" dest-id="169" weight="0.2245798975376391"/>
<connection id="875" src-id="190" dest-id="172" weight="1.4456282105476805"/>
<connection id="876" src-id="191" dest-id="180" weight="-0.8785994319552638"/>
<connection id="877" src-id="166" dest-id="191" weight="-2.1668468098877876"/>
<connection id="878" src-id="168" dest-id="167" weight="-2.5213606602193375"/>
<connection id="880" src-id="173" dest-id="167" weight="0.6392000913619995"/>
<connection id="882" src-id="185" dest-id="176" weight="1.2752744200008848"/>
<connection id="883" src-id="183" dest-id="167" weight="1.826279124210668"/>
<connection id="884" src-id="179" dest-id="166" weight="0.6610937459858569"/>
<connection id="885" src-id="191" dest-id="178" weight="-1.1915175599221248"/>
<connection id="887" src-id="191" dest-id="187" weight="2.3672625193721375"/>
<connection id="891" src-id="191" dest-id="188" weight="1.2258136909199018"/>
<connection id="896" src-id="175" dest-id="186" weight="1.5597694709014176"/>
<connection id="899" src-id="165" dest-id="173" weight="-0.9400807834303964"/>
<connection id="900" src-id="189" dest-id="180" weight="6.773052738913664"/>
<connection id="902" src-id="169" dest-id="188" weight="-0.19281470775604248"/>
<connection id="904" src-id="165" dest-id="184" weight="-1.6796714639340802"/>
<connection id="906" src-id="181" dest-id="167" weight="1.2095857314643197"/>
<connection id="907" src-id="184" dest-id="177" weight="-0.250352144241333"/>
<connection id="908" src-id="187" dest-id="165" weight="-2.749662410194966"/>
<connection id="909" src-id="177" dest-id="178" weight="-0.31573828522255853"/>
<connection id="910" src-id="175" dest-id="172" weight="-0.7238636092987591"/>
<connection id="911" src-id="184" dest-id="188" weight="1.0246800570925658"/>
<connection id="914" src-id="190" dest-id="190" weight="2.196595105720256"/>
<connection id="915" src-id="190" dest-id="165" weight="-0.5746312172817273"/>
<connection id="917" src-id="178" dest-id="170" weight="-0.6761232614517212"/>
<connection id="918" src-id="185" dest-id="184" weight="0.7966681718826294"/>
<connection id="919" src-id="179" dest-id="191" weight="0.045281052589416504"/>
<connection id="920" src-id="190" dest-id="180" weight="2.4955387811966903"/>
<connection id="923" src-id="189" dest-id="190" weight="-0.8863780498504639"/>
<connection id="924" src-id="191" dest-id="190" weight="0.5909614562988281"/>
<connection id="925" src-id="177" dest-id="181" weight="1.297022066392722"/>
<connection id="926" src-id="174" dest-id="167" weight="7.724049803404613"/>
<connection id="938" src-id="184" dest-id="181" weight="0.9319518804550171"/>
<connection id="939" src-id="189" dest-id="168" weight="-1.1663714645091132"/>
<connection id="940" src-id="180" dest-id="182" weight="0.7591839204720923"/>
<connection id="942" src-id="186" dest-id="176" weight="8.14185170662006"/>
<connection id="943" src-id="187" dest-id="176" weight="2.221336753212344"/>
<connection id="945" src-id="165" dest-id="166" weight="2.066987751200939"/>
<connection id="947" src-id="170" dest-id="179" weight="-3.3621870150826187"/>
<connection id="948" src-id="191" dest-id="176" weight="-1.5589572161370502"/>
<connection id="949" src-id="168" dest-id="182" weight="-0.7738698980203631"/>
<connection id="950" src-id="179" dest-id="183" weight="6.439476050218641"/>
<connection id="953" src-id="183" dest-id="186" weight="0.9055538410246879"/>
<connection id="954" src-id="186" dest-id="185" weight="0.722780704498291"/>
<connection id="955" src-id="191" dest-id="182" weight="-4.633284718563872"/>
<connection id="957" src-id="188" dest-id="180" weight="-0.8111654661162593"/>
<connection id="958" src-id="179" dest-id="167" weight="-0.49638770674138877"/>
<connection id="959" src-id="180" dest-id="183" weight="-0.3648970127105713"/>
<connection id="960" src-id="180" dest-id="188" weight="-1.4930799277737479"/>
<connection id="961" src-id="187" dest-id="184" weight="0.3273120268481803"/>
<connection id="962" src-id="168" dest-id="191" weight="-0.4497936964035034"/>
<connection id="963" src-id="167" dest-id="181" weight="-0.2686598311661429"/>
<connection id="964" src-id="178" dest-id="166" weight="-3.3076723047239267"/>
<connection id="965" src-id="184" dest-id="170" weight="1.545652719579563"/>
<connection id="966" src-id="170" dest-id="167" weight="1.9003217473048735"/>
<connection id="969" src-id="173" dest-id="183" weight="-0.1160435223398596"/>
<connection id="971" src-id="173" dest-id="169" weight="-0.6465549779368107"/>
<connection id="972" src-id="183" dest-id="176" weight="0.6779791116714478"/>
<connection id="974" src-id="173" dest-id="171" weight="-0.44761788845062256"/>
<connection id="975" src-id="169" dest-id="166" weight="-0.9143541457437454"/>
<connection id="991" src-id="190" dest-id="167" weight="1.2199214941017242"/>
<connection id="993" src-id="175" dest-id="173" weight="0.696696400642395"/>
<connection id="995" src-id="191" dest-id="168" weight="3.1024446611845473"/>
<connection id="996" src-id="166" dest-id="180" weight="-3.983419092858788"/>
<connection id="997" src-id="187" dest-id="189" weight="-4.641486147844187"/>
<connection id="998" src-id="174" dest-id="175" weight="-0.06689141197112303"/>
<connection id="1005" src-id="170" dest-id="186" weight="3.6257438537988342"/>
<connection id="1007" src-id="191" dest-id="184" weight="-2.1855862247529796"/>
<connection id="1009" src-id="170" dest-id="183" weight="1.5904096615133627"/>
<connection id="1013" src-id="187" dest-id="179" weight="-0.18510348759485568"/>
<connection id="1014" src-id="172" dest-id="170" weight="5.583209976053558"/>
<connection id="1016" src-id="173" dest-id="182" weight="-8.04534090293489"/>
<connection id="1027" src-id="181" dest-id="173" weight="0.704328179359436"/>
<connection id="1028" src-id="170" dest-id="170" weight="-0.48956358432769775"/>
<connection id="1030" src-id="189" dest-id="181" weight="-0.43861982028375035"/>
<connection id="1099" src-id="182" dest-id="187" weight="-0.6328269116285362"/>
<connection id="1100" src-id="186" dest-id="171" weight="0.513300895690918"/>
<connection id="1144" src-id="182" dest-id="175" weight="0.7136678207285205"/>
<neuron id="1607" type="hid" activation="sigmoid"/>
<connection id="1608" src-id="187" dest-id="1607" weight="2.1220265004195262"/>
<connection id="1621" src-id="171" dest-id="1607" weight="-6.724553797850566"/>
<connection id="1622" src-id="175" dest-id="1607" weight="-0.8817555550005671"/>
<connection id="1623" src-id="1607" dest-id="175" weight="-8.965095860019908"/>
<connection id="1625" src-id="169" dest-id="1607" weight="3.328050508321179"/>
<connection id="1626" src-id="182" dest-id="1607" weight="-6.694046711419107"/>
<connection id="1638" src-id="1607" dest-id="189" weight="-0.6712545213288754"/>
<connection id="1639" src-id="1607" dest-id="183" weight="-0.3555169105529785"/>
<connection id="1641" src-id="1607" dest-id="184" weight="-1.1773259354731356"/>
<connection id="1642" src-id="1607" dest-id="185" weight="0.1561211347579956"/>
<connection id="1643" src-id="1607" dest-id="187" weight="3.7250978646161177"/>
<connection id="1659" src-id="178" dest-id="1607" weight="-3.380220730600284"/>
<connection id="1663" src-id="170" dest-id="1607" weight="-1.3580237134671242"/>
<connection id="1664" src-id="1607" dest-id="168" weight="4.256580073514628"/>
<connection id="1690" src-id="1607" dest-id="186" weight="-7.136552038791081"/>
<connection id="1759" src-id="1607" dest-id="188" weight="4.507280843788676"/>
<connection id="1760" src-id="1607" dest-id="181" weight="1.8444885923599572"/>
<connection id="1773" src-id="189" dest-id="1607" weight="-0.014632344245910645"/>
<connection id="1774" src-id="1607" dest-id="180" weight="-1.343349022139329"/>
<connection id="1788" src-id="191" dest-id="1607" weight="4.697700770511675"/>
<connection id="1804" src-id="167" dest-id="1607" weight="1.1820116221195502"/>
<connection id="1807" src-id="1607" dest-id="1607" weight="0.5459370332196067"/>
<connection id="1893" src-id="1607" dest-id="172" weight="-0.2869352102279663"/>
<connection id="1894" src-id="1607" dest-id="169" weight="-0.20787310600280762"/>
<connection id="1963" src-id="183" dest-id="1607" weight="2.046532902105065"/>
<connection id="2009" src-id="1607" dest-id="176" weight="-2.02689556353917"/>
<connection id="2010" src-id="1607" dest-id="177" weight="-0.148021471421793"/>
<connection id="2076" src-id="1607" dest-id="190" weight="0.13089847564697266"/>
<connection id="2144" src-id="181" dest-id="1607" weight="0.8133603009641139"/>
<connection id="2162" src-id="1607" dest-id="179" weight="0.41141068935394287"/>
<neuron id="2210" type="hid" activation="sigmoid"/>
<connection id="2211" src-id="192" dest-id="2210" weight="-0.9396768929415715"/>
<connection id="2212" src-id="2210" dest-id="183" weight="0.8428907869355502"/>
<neuron id="2213" type="hid" activation="sigmoid"/>
<connection id="2214" src-id="173" dest-id="2213" weight="0.5550861358642578"/>
<connection id="2235" src-id="2213" dest-id="187" weight="3.195753267072485"/>
<connection id="2237" src-id="2213" dest-id="185" weight="-0.7816104888916016"/>
<connection id="2238" src-id="189" dest-id="2213" weight="-6.247619148797471"/>
<connection id="2239" src-id="180" dest-id="2210" weight="-5.157189464704181"/>
<connection id="2241" src-id="2213" dest-id="2210" weight="-0.24296876912973664"/>
<connection id="2242" src-id="2210" dest-id="2213" weight="-0.10068050468910224"/>
<connection id="2243" src-id="165" dest-id="2210" weight="-1.7832144933614824"/>
<connection id="2245" src-id="191" dest-id="2210" weight="0.1353938216836834"/>
<connection id="2246" src-id="2210" dest-id="190" weight="2.7670045202198765"/>
<connection id="2248" src-id="2210" dest-id="174" weight="-0.1300196647644043"/>
<connection id="2249" src-id="2213" dest-id="174" weight="-3.797680650314544"/>
<connection id="2250" src-id="2213" dest-id="181" weight="0.8477912289320922"/>
<connection id="2253" src-id="2210" dest-id="185" weight="-4.290430794466677"/>
<connection id="2254" src-id="187" dest-id="2210" weight="1.711239569002053"/>
<connection id="2255" src-id="2210" dest-id="168" weight="0.48177823127022235"/>
<connection id="2271" src-id="2210" dest-id="176" weight="-3.9712615233229416"/>
<connection id="2274" src-id="2210" dest-id="182" weight="-3.268508687745686"/>
<connection id="2281" src-id="2213" dest-id="188" weight="-1.2063425228451852"/>
<connection id="2282" src-id="186" dest-id="2213" weight="4.700902611539968"/>
<connection id="2283" src-id="2210" dest-id="179" weight="-0.6724165678024292"/>
<connection id="2285" src-id="185" dest-id="2210" weight="8.510350168974348"/>
<connection id="2287" src-id="2210" dest-id="178" weight="-0.08655477721096522"/>
<connection id="2289" src-id="170" dest-id="2213" weight="0.9094002422677677"/>
<connection id="2290" src-id="178" dest-id="2210" weight="-2.0277418625390884"/>
<connection id="2314" src-id="2213" dest-id="180" weight="-3.7652630754090133"/>
<connection id="2315" src-id="169" dest-id="2213" weight="-1.294553811218151"/>
<connection id="2316" src-id="173" dest-id="2210" weight="-3.0029969738078806"/>
<connection id="2318" src-id="177" dest-id="2213" weight="-0.8426750898361206"/>
<connection id="2320" src-id="176" dest-id="2210" weight="0.6329728057523422"/>
<connection id="2321" src-id="2210" dest-id="186" weight="6.305780381614133"/>
<connection id="2323" src-id="175" dest-id="2213" weight="-4.071704016465057"/>
<connection id="2324" src-id="192" dest-id="2213" weight="-1.4188891848073955"/>
<connection id="2325" src-id="2210" dest-id="165" weight="0.38568317890167236"/>
<connection id="2326" src-id="177" dest-id="2210" weight="1.9600805480998638"/>
<connection id="2347" src-id="175" dest-id="2210" weight="1.4462431357577967"/>
<connection id="2348" src-id="188" dest-id="2213" weight="-1.9122198795141399"/>
<connection id="2349" src-id="182" dest-id="2210" weight="2.7558493411443097"/>
<connection id="2350" src-id="2213" dest-id="191" weight="0.7022500038146973"/>
<connection id="2351" src-id="2210" dest-id="189" weight="-0.25934660107345975"/>
<connection id="2352" src-id="183" dest-id="2210" weight="3.6245050042535207"/>
<connection id="2362" src-id="2213" dest-id="171" weight="3.717670435745482"/>
<connection id="2364" src-id="2210" dest-id="170" weight="-1.606641924185523"/>
<connection id="2380" src-id="2213" dest-id="176" weight="1.032547572892177"/>
<connection id="2381" src-id="187" dest-id="2213" weight="-0.7361849248852308"/>
<connection id="2382" src-id="2213" dest-id="166" weight="1.3234483979119909"/>
<connection id="2386" src-id="2210" dest-id="172" weight="-0.41405022144317627"/>
<connection id="2387" src-id="2213" dest-id="184" weight="0.9525902271270752"/>
<connection id="2388" src-id="2210" dest-id="167" weight="0.061083724447754784"/>
<connection id="2389" src-id="166" dest-id="2213" weight="3.2388809459289076"/>
<connection id="2397" src-id="2213" dest-id="167" weight="-0.7958080575626129"/>
<connection id="2398" src-id="2210" dest-id="171" weight="4.373427554700087"/>
<connection id="2399" src-id="2213" dest-id="172" weight="-0.5564992427825928"/>
<connection id="2401" src-id="2213" dest-id="182" weight="-0.8496551513671875"/>
<connection id="2402" src-id="172" dest-id="2213" weight="-1.6972776198489024"/>
<connection id="2403" src-id="2213" dest-id="189" weight="-0.16785879687323527"/>
<connection id="2404" src-id="168" dest-id="2213" weight="-0.18570208549499512"/>
<connection id="2420" src-id="184" dest-id="2213" weight="1.7831614518649697"/>
<connection id="2421" src-id="2210" dest-id="191" weight="2.8139080741312124"/>
<connection id="2426" src-id="2210" dest-id="2210" weight="-0.3620554208755493"/>
<connection id="2457" src-id="190" dest-id="2210" weight="-0.8338981866836548"/>
<connection id="2465" src-id="191" dest-id="2213" weight="-7.136879673503199"/>
<connection id="2468" src-id="185" dest-id="2213" weight="4.465869609930209"/>
<connection id="2469" src-id="2210" dest-id="173" weight="-2.4728171470476674"/>
<connection id="2496" src-id="2213" dest-id="183" weight="0.9080572128295898"/>
<connection id="2910" src-id="2210" dest-id="1607" weight="-0.29876617105674397"/>
<connection id="2931" src-id="1607" dest-id="170" weight="-2.423699836325532"/>
<neuron id="2968" type="hid" activation="sigmoid"/>
<connection id="2992" src-id="189" dest-id="2968" weight="-0.5937451124191284"/>
<connection id="2993" src-id="170" dest-id="2968" weight="0.8816867630868962"/>
<connection id="2994" src-id="190" dest-id="2968" weight="-0.5795087111842603"/>
<connection id="2995" src-id="191" dest-id="2968" weight="0.8646902250651312"/>
<connection id="2996" src-id="2968" dest-id="166" weight="-0.8597393035888672"/>
<connection id="3019" src-id="2968" dest-id="186" weight="-6.186902312220455"/>
<connection id="3020" src-id="192" dest-id="2968" weight="0.822669267654419"/>
<connection id="3021" src-id="1607" dest-id="2213" weight="-0.33476531505584717"/>
<connection id="3023" src-id="184" dest-id="2968" weight="1.9126292383091497"/>
<connection id="3024" src-id="2968" dest-id="192" weight="-0.3312124013900757"/>
<connection id="3027" src-id="2968" dest-id="174" weight="0.6218792200088501"/>
<connection id="3028" src-id="179" dest-id="2968" weight="0.5340638374941005"/>
<connection id="3030" src-id="2968" dest-id="1607" weight="-0.5722482204437256"/>
<neuron id="3033" type="hid" activation="sigmoid"/>
<connection id="3057" src-id="2968" dest-id="170" weight="0.5806154012680054"/>
<connection id="3058" src-id="186" dest-id="3033" weight="1.4676338118480456"/>
<connection id="3059" src-id="3033" dest-id="183" weight="-0.6903324127197266"/>
<connection id="3060" src-id="3033" dest-id="167" weight="1.185184048266732"/>
<connection id="3061" src-id="168" dest-id="1607" weight="0.47179174423217773"/>
<connection id="3062" src-id="3033" dest-id="188" weight="5.283087857235212"/>
<connection id="3063" src-id="165" dest-id="2968" weight="-2.3776108247771015"/>
<connection id="3064" src-id="176" dest-id="2968" weight="-0.24465009855356024"/>
<connection id="3066" src-id="3033" dest-id="3033" weight="-2.4753516971040126"/>
<connection id="3067" src-id="2210" dest-id="3033" weight="0.6002890343509406"/>
<connection id="3068" src-id="2968" dest-id="189" weight="-0.5126553845067983"/>
<connection id="3070" src-id="2968" dest-id="183" weight="7.569687432908818"/>
<connection id="3071" src-id="173" dest-id="2968" weight="2.8632057568929365"/>
<connection id="3072" src-id="2968" dest-id="167" weight="1.0429992451352001"/>
<connection id="3119" src-id="166" dest-id="3033" weight="-0.9447034793220659"/>
<connection id="3121" src-id="170" dest-id="3033" weight="0.6682319471415017"/>
<connection id="3122" src-id="187" dest-id="2968" weight="-1.2513801135615965"/>
<connection id="3125" src-id="190" dest-id="3033" weight="-0.3112199097394246"/>
<connection id="3127" src-id="168" dest-id="2968" weight="-2.8359718580515088"/>
<connection id="3128" src-id="3033" dest-id="169" weight="0.5777209679849291"/>
<connection id="3129" src-id="3033" dest-id="192" weight="-0.022468924522399902"/>
<connection id="3130" src-id="185" dest-id="2968" weight="6.432259643583182"/>
<connection id="3131" src-id="1607" dest-id="3033" weight="3.1743833053433717"/>
<connection id="3132" src-id="192" dest-id="3033" weight="0.09125685691833496"/>
<connection id="3137" src-id="2968" dest-id="169" weight="-1.6651109514586748"/>
<connection id="3138" src-id="3033" dest-id="175" weight="-2.9717539414341725"/>
<connection id="3140" src-id="3033" dest-id="182" weight="0.6551366810763652"/>
<connection id="3157" src-id="3033" dest-id="171" weight="0.23332560062408447"/>
<connection id="3158" src-id="176" dest-id="3033" weight="-12.436602885563888"/>
<connection id="3159" src-id="171" dest-id="3033" weight="0.40824592113494873"/>
<connection id="3160" src-id="178" dest-id="2968" weight="0.7208918333053589"/>
<connection id="3162" src-id="182" dest-id="3033" weight="0.7452930212020874"/>
<connection id="3163" src-id="2968" dest-id="180" weight="0.1261659860610962"/>
<connection id="3164" src-id="174" dest-id="2968" weight="-0.139387845993042"/>
<connection id="3166" src-id="3033" dest-id="179" weight="0.3794136781510925"/>
<connection id="3167" src-id="188" dest-id="3033" weight="0.4908205557116645"/>
<connection id="3170" src-id="188" dest-id="2968" weight="-7.119114249943993"/>
<connection id="3171" src-id="175" dest-id="3033" weight="0.12270133090899649"/>
<connection id="3172" src-id="191" dest-id="3033" weight="0.5229783058166504"/>
<connection id="3173" src-id="3033" dest-id="174" weight="2.3137058862262307"/>
<connection id="3189" src-id="2968" dest-id="187" weight="-1.6324235181657119"/>
<connection id="3190" src-id="174" dest-id="3033" weight="0.4475734533512856"/>
<connection id="3192" src-id="3033" dest-id="2968" weight="5.4966640077358875"/>
<connection id="3196" src-id="3033" dest-id="180" weight="2.656158682705588"/>
<connection id="3198" src-id="3033" dest-id="187" weight="-0.47511755145955864"/>
<connection id="3200" src-id="2213" dest-id="2968" weight="1.918059789238907"/>
<connection id="3202" src-id="168" dest-id="3033" weight="-1.3966319425725846"/>
<connection id="3203" src-id="3033" dest-id="166" weight="0.03731502408087306"/>
<connection id="3204" src-id="179" dest-id="3033" weight="1.5580134185652421"/>
<connection id="3228" src-id="2968" dest-id="3033" weight="2.1898877020820033"/>
<connection id="3229" src-id="2968" dest-id="2968" weight="-3.0275107486235306"/>
<connection id="3230" src-id="178" dest-id="3033" weight="0.18714378410309607"/>
<connection id="3248" src-id="2213" dest-id="3033" weight="0.3849691152572632"/>
<connection id="3249" src-id="2968" dest-id="179" weight="3.2008595926156183"/>
<connection id="3266" src-id="172" dest-id="3033" weight="-0.24119722843170166"/>
<connection id="3268" src-id="180" dest-id="3033" weight="-0.6399492025375366"/>
<connection id="3269" src-id="186" dest-id="2968" weight="-0.06592988967895508"/>
<connection id="3298" src-id="184" dest-id="3033" weight="-0.6197272539138794"/>
<connection id="3317" src-id="3033" dest-id="186" weight="-0.8258482428738504"/>
<connection id="3318" src-id="183" dest-id="3033" weight="0.5412123203277588"/>
<connection id="3328" src-id="2968" dest-id="188" weight="-2.909192470725552"/>
<connection id="3366" src-id="3033" dest-id="181" weight="-5.802568834286523"/>
<connection id="3391" src-id="2968" dest-id="185" weight="0.47931158542633057"/>
<neuron id="3741" type="hid" activation="sigmoid"/>
<connection id="3760" src-id="3741" dest-id="174" weight="-1.9808652825116577"/>
<connection id="3761" src-id="3741" dest-id="189" weight="-0.6724209877331095"/>
<connection id="3762" src-id="3741" dest-id="179" weight="-0.03661032090288312"/>
<connection id="3763" src-id="174" dest-id="3741" weight="-0.7916867934907776"/>
<connection id="3765" src-id="1607" dest-id="3741" weight="-1.2227344072108668"/>
<connection id="3771" src-id="175" dest-id="3741" weight="-0.6216442584991455"/>
<connection id="3772" src-id="3741" dest-id="2213" weight="-1.7383086117337623"/>
<connection id="3773" src-id="3741" dest-id="2210" weight="0.3321351479239647"/>
<connection id="3792" src-id="3741" dest-id="2968" weight="0.025631427764892578"/>
<connection id="3793" src-id="3741" dest-id="186" weight="-0.7594296932220459"/>
<connection id="3795" src-id="2213" dest-id="3741" weight="-1.6273392690046777"/>
<connection id="3796" src-id="3741" dest-id="165" weight="-1.2530478209489928"/>
<connection id="3801" src-id="3741" dest-id="1607" weight="-2.5822187861584758"/>
<connection id="3802" src-id="179" dest-id="3741" weight="2.918979423567236"/>
<connection id="3804" src-id="168" dest-id="3741" weight="3.197913393092514"/>
<connection id="3828" src-id="189" dest-id="3741" weight="-0.09698924011459875"/>
<connection id="3829" src-id="3741" dest-id="188" weight="3.655472158432249"/>
<connection id="3838" src-id="188" dest-id="3741" weight="-0.3772505219399729"/>
<connection id="3839" src-id="3741" dest-id="177" weight="-2.4106533434392916"/>
<connection id="3842" src-id="3741" dest-id="169" weight="0.26174116134643555"/>
<connection id="3844" src-id="3741" dest-id="3741" weight="6.8023036723383665"/>
<connection id="3864" src-id="181" dest-id="3741" weight="-0.11616537513102254"/>
<connection id="3867" src-id="176" dest-id="3741" weight="-0.5890033324256227"/>
<connection id="3869" src-id="171" dest-id="3741" weight="0.8163567781448364"/>
<connection id="3871" src-id="3741" dest-id="166" weight="-0.2013036012649536"/>
<connection id="3872" src-id="3741" dest-id="181" weight="-3.020441075906148"/>
<connection id="3874" src-id="167" dest-id="3741" weight="0.9054784774780273"/>
<connection id="3891" src-id="3741" dest-id="183" weight="0.9900217056274414"/>
<connection id="3892" src-id="172" dest-id="3741" weight="-3.2683820449147105"/>
<connection id="3895" src-id="192" dest-id="3741" weight="1.4809868028083808"/>
<connection id="3920" src-id="3741" dest-id="192" weight="-4.264783978794432"/>
<connection id="3921" src-id="187" dest-id="3741" weight="-1.7744066277216142"/>
<connection id="3923" src-id="3741" dest-id="170" weight="-0.5148923397064209"/>
<connection id="3931" src-id="3741" dest-id="178" weight="-1.2465725632255615"/>
<connection id="3947" src-id="180" dest-id="3741" weight="-2.523454733673633"/>
<connection id="3953" src-id="3741" dest-id="167" weight="-0.5902009193504201"/>
<neuron id="4531" type="hid" activation="sigmoid"/>
<connection id="4575" src-id="4531" dest-id="173" weight="-0.7959413528442383"/>
<connection id="4579" src-id="178" dest-id="4531" weight="1.4259612899080905"/>
<connection id="4580" src-id="165" dest-id="4531" weight="0.687883217048552"/>
<connection id="4581" src-id="1607" dest-id="4531" weight="-1.9844124378047865"/>
<connection id="4585" src-id="4531" dest-id="181" weight="2.300562681430929"/>
<connection id="4628" src-id="4531" dest-id="1607" weight="-0.7911622524261475"/>
<connection id="4631" src-id="179" dest-id="4531" weight="-0.7933121919631958"/>
<connection id="4634" src-id="187" dest-id="4531" weight="-2.533886094263668"/>
<connection id="4705" src-id="2210" dest-id="4531" weight="1.5357299655459502"/>
<connection id="4706" src-id="169" dest-id="4531" weight="-0.37419898871222546"/>
<connection id="4790" src-id="168" dest-id="4531" weight="2.8068018225372384"/>
<connection id="4791" src-id="185" dest-id="4531" weight="-0.562089204788208"/>
<connection id="4792" src-id="172" dest-id="4531" weight="1.86161723471395"/>
<connection id="4793" src-id="3033" dest-id="4531" weight="-0.7290022868108506"/>
<connection id="4795" src-id="177" dest-id="4531" weight="0.07725885864548658"/>
<connection id="4796" src-id="4531" dest-id="192" weight="1.2509512934045357"/>
<connection id="4822" src-id="4531" dest-id="190" weight="-1.020103776981593"/>
<connection id="4872" src-id="4531" dest-id="182" weight="0.1560661792755127"/>
<connection id="4874" src-id="4531" dest-id="172" weight="0.36798903465045985"/>
<connection id="4903" src-id="4531" dest-id="176" weight="-1.5548097706851576"/>
<connection id="4904" src-id="4531" dest-id="191" weight="-0.08679726385770759"/>
<connection id="4905" src-id="167" dest-id="4531" weight="3.8888746038066735"/>
<connection id="4996" src-id="191" dest-id="4531" weight="-0.6030333042144775"/>
<connection id="4997" src-id="4531" dest-id="2210" weight="4.182015773757243"/>
<connection id="5005" src-id="184" dest-id="4531" weight="-3.7769239989526913"/>
<connection id="5006" src-id="4531" dest-id="180" weight="-1.3239289686633584"/>
<connection id="5008" src-id="4531" dest-id="184" weight="-3.495145134258424"/>
<connection id="5009" src-id="4531" dest-id="2968" weight="-5.278138573561173"/>
<connection id="5010" src-id="190" dest-id="4531" weight="0.16573405265808105"/>
<connection id="5053" src-id="4531" dest-id="168" weight="0.956537050336614"/>
<connection id="5178" src-id="4531" dest-id="174" weight="0.9873090982437134"/>
<connection id="5216" src-id="4531" dest-id="3741" weight="-4.341597819331205"/>
<connection id="5266" src-id="2968" dest-id="4531" weight="2.3322778301405473"/>
<connection id="5315" src-id="174" dest-id="4531" weight="-0.29034388690272883"/>
<connection id="5334" src-id="166" dest-id="4531" weight="-0.3672133958947197"/>
<connection id="5515" src-id="4531" dest-id="189" weight="0.8389236927032471"/>
<neuron id="5529" type="hid" activation="sigmoid"/>
<connection id="5531" src-id="5529" dest-id="167" weight="0.17337286472320557"/>
<connection id="5552" src-id="5529" dest-id="191" weight="-2.0193279937618556"/>
<connection id="5554" src-id="2213" dest-id="5529" weight="-0.8649828433990479"/>
<connection id="5556" src-id="5529" dest-id="165" weight="1.7569018931239238"/>
<connection id="5557" src-id="3033" dest-id="5529" weight="-2.6214524063335856"/>
<connection id="5558" src-id="175" dest-id="5529" weight="-1.9183609953778205"/>
<connection id="5619" src-id="185" dest-id="5529" weight="-1.2238838518142832"/>
<connection id="5621" src-id="186" dest-id="5529" weight="-1.4376396385499695"/>
<connection id="5623" src-id="5529" dest-id="178" weight="-0.9620381593704224"/>
<connection id="5624" src-id="5529" dest-id="182" weight="2.733723900860332"/>
<connection id="5671" src-id="5529" dest-id="181" weight="-4.026390397721717"/>
<connection id="5672" src-id="5529" dest-id="170" weight="-0.26266812908024506"/>
<connection id="5674" src-id="5529" dest-id="192" weight="0.9751501083374023"/>
<connection id="5676" src-id="176" dest-id="5529" weight="1.9139773386454122"/>
<connection id="5705" src-id="5529" dest-id="185" weight="3.7154040219842006"/>
<connection id="5707" src-id="189" dest-id="5529" weight="1.5157340099142655"/>
<connection id="5718" src-id="170" dest-id="4531" weight="-0.047560945693819474"/>
<connection id="5752" src-id="172" dest-id="5529" weight="0.5646950006484985"/>
<connection id="5753" src-id="5529" dest-id="188" weight="-1.0271406450152205"/>
<connection id="5754" src-id="5529" dest-id="186" weight="-2.4408056828806606"/>
<connection id="5755" src-id="167" dest-id="5529" weight="1.5860876644818416"/>
<connection id="5820" src-id="5529" dest-id="2968" weight="1.5575415684909113"/>
<connection id="5822" src-id="5529" dest-id="184" weight="-0.49232447147369385"/>
<connection id="5823" src-id="5529" dest-id="3033" weight="-4.556089661914237"/>
<connection id="5860" src-id="5529" dest-id="175" weight="0.7552362680435181"/>
<connection id="5937" src-id="5529" dest-id="172" weight="4.725214185148378"/>
<connection id="5938" src-id="177" dest-id="5529" weight="0.4624241590499878"/>
<connection id="6032" src-id="192" dest-id="5529" weight="-0.27793003810893485"/>
<connection id="6033" src-id="5529" dest-id="174" weight="-0.8776067495346069"/>
<connection id="6035" src-id="5529" dest-id="183" weight="-2.071626013483294"/>
<connection id="6095" src-id="5529" dest-id="176" weight="1.2505813682856908"/>
<connection id="6097" src-id="5529" dest-id="2210" weight="-0.6094697943378145"/>
<connection id="6134" src-id="190" dest-id="5529" weight="-0.7003788197566281"/>
<connection id="6197" src-id="5529" dest-id="190" weight="0.815902590751648"/>
<connection id="6198" src-id="166" dest-id="5529" weight="-1.050639730154992"/>
<connection id="6207" src-id="5529" dest-id="2213" weight="0.3192082057121819"/>
<connection id="6208" src-id="5529" dest-id="169" weight="2.4064881111304044"/>
<connection id="6331" src-id="171" dest-id="5529" weight="0.8017287254333496"/>
<connection id="6370" src-id="181" dest-id="5529" weight="0.23161077499389648"/>
<connection id="6459" src-id="5529" dest-id="177" weight="-2.4964072737634293"/>
<connection id="6487" src-id="168" dest-id="5529" weight="1.8676525664317212"/>
<connection id="6533" src-id="170" dest-id="5529" weight="-0.07614842149740908"/>
<neuron id="6656" type="hid" activation="sigmoid"/>
<connection id="6657" src-id="3033" dest-id="6656" weight="2.56115422170211"/>
<connection id="6687" src-id="6656" dest-id="189" weight="0.20116961002349854"/>
<connection id="6689" src-id="6656" dest-id="188" weight="-0.9114526510238647"/>
<connection id="6711" src-id="170" dest-id="6656" weight="0.5715032815933228"/>
<connection id="6712" src-id="6656" dest-id="4531" weight="-0.3958771228790283"/>
<connection id="6714" src-id="6656" dest-id="178" weight="1.7794859497057587"/>
<connection id="6734" src-id="169" dest-id="6656" weight="-0.7979131937026978"/>
<connection id="6735" src-id="172" dest-id="6656" weight="0.318467378616333"/>
<connection id="6737" src-id="6656" dest-id="171" weight="0.9184026718139648"/>
<connection id="6760" src-id="188" dest-id="6656" weight="-0.9464050531387329"/>
<connection id="6784" src-id="6656" dest-id="167" weight="-0.3168242164950037"/>
<connection id="6785" src-id="6656" dest-id="175" weight="-0.5263457355112122"/>
<connection id="6791" src-id="6656" dest-id="186" weight="-0.6019426584243774"/>
<connection id="6827" src-id="5529" dest-id="6656" weight="-0.9246207475662231"/>
<connection id="6828" src-id="6656" dest-id="2968" weight="-0.9946203768368902"/>
<connection id="6829" src-id="191" dest-id="6656" weight="1.1047027224501211"/>
<connection id="6833" src-id="6656" dest-id="191" weight="2.949089441904948"/>
<connection id="6835" src-id="165" dest-id="6656" weight="-0.7091887181017016"/>
<connection id="6836" src-id="177" dest-id="6656" weight="-0.582841942996405"/>
<connection id="6837" src-id="185" dest-id="6656" weight="2.5879015836102504"/>
<connection id="6852" src-id="6656" dest-id="168" weight="-3.2510145038821907"/>
<connection id="6869" src-id="3741" dest-id="6656" weight="1.6289458655581988"/>
<connection id="6870" src-id="184" dest-id="6656" weight="2.1337915846606097"/>
<connection id="6874" src-id="1607" dest-id="6656" weight="-0.17649228035031359"/>
<connection id="6903" src-id="166" dest-id="6656" weight="-0.5038597583770752"/>
<connection id="6921" src-id="6656" dest-id="169" weight="-3.1327819350353847"/>
<connection id="6922" src-id="192" dest-id="6656" weight="1.2533434357314488"/>
<connection id="6943" src-id="6656" dest-id="177" weight="0.6416048196910102"/>
<connection id="6953" src-id="183" dest-id="6656" weight="0.9880892038345337"/>
<connection id="7265" src-id="6656" dest-id="2210" weight="0.4402534220797292"/>
</chromosome>